CHANGELOG.md
casparser_isin/__init__.py
casparser_isin/cli.py
casparser_isin/isin.db
casparser_isin/isin.py
casparser_isin/mf_isin.py
casparser_isin/utils.py
casparser_isin-2025.3.1.dist-info/METADATA
casparser_isin-2025.3.1.dist-info/WHEEL
casparser_isin-2025.3.1.dist-info/entry_points.txt
casparser_isin-2025.3.1.dist-info/licenses/LICENSE
casparser_isin-2025.3.1.dist-info/RECORD
