Metadata-Version: 2.4
Name: casparser_isin
Version: 2025.3.1
Summary: ISIN database for casparser
Project-URL: Homepage, https://github.com/codereverser/casparser-isin
Author-email: Sandeep Somasekharan <codereverser@gmail.com>
License-Expression: MIT
License-File: LICENSE
Classifier: License :: OSI Approved :: MIT License
Classifier: Operating System :: OS Independent
Classifier: Programming Language :: Python :: 3.9
Classifier: Programming Language :: Python :: 3.10
Classifier: Programming Language :: Python :: 3.11
Classifier: Programming Language :: Python :: 3.12
Classifier: Programming Language :: Python :: 3.13
Requires-Python: ~=3.9
Requires-Dist: packaging>=20.9
Requires-Dist: rapidfuzz<4,>=3.12.0
